catly_translate/__init__.py
catly_translate/__version.py
catly_translate/js_test.py
catly_translate/sign.js
catly_translate/utils.py
catly_translate-0.1.2.dist-info/METADATA
catly_translate-0.1.2.dist-info/WHEEL
catly_translate-0.1.2.dist-info/top_level.txt
catly_translate-0.1.2.dist-info/RECORD
