Metadata-Version: 2.1
Name: catly-translate
Version: 0.1.2
Summary: Simple & Easy Way For Baidu Translation
Home-page: https://github.com/CatNeverCodes/catly_translate
Author: CatNeverCodes
Author-email: 574469831@qq.com
License: UNKNOWN
Keywords: translate,translation,baidu,Baidu,BAIDU,百度翻译,baidu translate,python3
Platform: UNKNOWN
Classifier: Programming Language :: Python :: 3
Requires-Dist: httpx
Requires-Dist: PyExecJS
